tag_spy/__init__.py
tag_spy/_version.py
tag_spy/api.py
tag_spy/cli.py
tag_spy/client_factory.py
tag_spy/filter_helpers.py
tag_spy/http_client.py
tag_spy/image_tag_triple.py
tag_spy/opener_factory.py
tag_spy/registry_helpers.py
tag_spy-0.5.0.dist-info/LICENSE
tag_spy-0.5.0.dist-info/METADATA
tag_spy-0.5.0.dist-info/WHEEL
tag_spy-0.5.0.dist-info/entry_points.txt
tag_spy-0.5.0.dist-info/top_level.txt
tag_spy-0.5.0.dist-info/zip-safe
tag_spy-0.5.0.dist-info/RECORD
