Metadata-Version: 2.1
Name: tag-spy
Version: 0.5.0
Summary: Identify the latest DD-DeCaF tag on a particular Docker image.
Home-page: https://github.com/dd-decaf/tag-spy
Author: Novo Nordisk Foundation Center for Biosustainability, Technical University of Denmark
Author-email: niso@biosustain.dtu.dk
License: Apache-2.0
Download-URL: https://pypi.org/project/tag-spy/
Keywords: Docker,image,tag,latest
Platform: UNKNOWN
Classifier: Development Status :: 2 - Pre-Alpha
Classifier: Intended Audience :: Developers
Classifier: License :: OSI Approved :: Apache Software License
Classifier: Natural Language :: English
Classifier: Operating System :: OS Independent
Classifier: Programming Language :: Python :: 3 :: Only
Classifier: Programming Language :: Python :: 3.7
Classifier: Programming Language :: Python :: 3.8
Classifier: Programming Language :: Python :: 3.9
Classifier: Topic :: Software Development
Classifier: Topic :: Utilities
Classifier: Typing :: Typed
Requires-Python: >=3.7
Provides-Extra: development
Requires-Dist: black ; extra == 'development'
Requires-Dist: isort ; extra == 'development'
Requires-Dist: tox ; extra == 'development'
